pyroborock/__init__.py
pyroborock-1.0.10.dist-info/METADATA
pyroborock-1.0.10.dist-info/WHEEL
pyroborock-1.0.10.dist-info/top_level.txt
pyroborock-1.0.10.dist-info/RECORD
