Metadata-Version: 2.1
Name: pyroborock
Version: 1.0.10
Summary: Communicate with roborock over tuya protocol
Home-page: https://github.com/89jd/pyroborock
Author: jd89
Author-email: jd89.dev@gmail.com
License: UNKNOWN
Platform: UNKNOWN
Requires-Dist: pytuyapi-ipc (==1.0.4)
Requires-Dist: python-miio (==0.5.3)
Requires-Dist: pycryptodome (==3.9.8)
